django_model_serializer/Serializer.py
django_model_serializer/__init__.py
django_model_serializer-0.1.0.dist-info/LICENSE
django_model_serializer-0.1.0.dist-info/METADATA
django_model_serializer-0.1.0.dist-info/WHEEL
django_model_serializer-0.1.0.dist-info/top_level.txt
django_model_serializer-0.1.0.dist-info/RECORD
