Metadata-Version: 2.1
Name: django-model-serializer
Version: 0.1.0
Summary: Convert Django model instance to dict type (Json)
Home-page: https://gitlab.com/Mahdi1419/django-model-serializer
Author: Mahdi Bagherzade
Author-email: mahdib999@gmail.com
License: UNKNOWN
Project-URL: Bug Tracker, https://gitlab.com/Mahdi1419/django-model-serializer/issues
Platform: UNKNOWN
Classifier: Programming Language :: Python :: 3
Classifier: License :: OSI Approved :: MIT License
Classifier: Operating System :: OS Independent
Requires-Python: >=3.6
License-File: LICENSE
